clidoro/__init__.py
clidoro/_utils.py
clidoro/chart.py
clidoro/clidoro.png
clidoro/clidoro.py
clidoro/data.py
clidoro/termgraph/__init__.py
clidoro/termgraph/_termgraph.py
clidoro/termgraph/module.py
clidoro/termgraph/utils.py
clidoro-0.1.5.dist-info/METADATA
clidoro-0.1.5.dist-info/WHEEL
clidoro-0.1.5.dist-info/entry_points.txt
clidoro-0.1.5.dist-info/top_level.txt
clidoro-0.1.5.dist-info/RECORD
